secret_scan-0.1.2.dist-info/licenses/LICENSE
secret_scanner/cli.py
secret_scanner/patterns.py
secret_scanner/scanner.py
secret_scan-0.1.2.dist-info/METADATA
secret_scan-0.1.2.dist-info/WHEEL
secret_scan-0.1.2.dist-info/entry_points.txt
secret_scan-0.1.2.dist-info/top_level.txt
secret_scan-0.1.2.dist-info/RECORD
