Metadata-Version: 2.4
Name: secret-scan
Version: 0.1.2
Summary: A simple secret/credential scanner for source code repositories.
Author-email: Your Name <you@example.com>
License: MIT License
Project-URL: Homepage, https://github.com/harshahemanth/secret-scan
Project-URL: Repository, https://github.com/harshahemanth/secret-scan
Project-URL: Issues, https://github.com/harshahemanth/secret-scan/issues
Project-URL: Documentation, https://github.com/harshahemanth/secret-scan#readme
Keywords: security,secrets,credentials,scanner
Classifier: Programming Language :: Python :: 3
Classifier: License :: OSI Approved :: MIT License
Classifier: Environment :: Console
Classifier: Intended Audience :: Developers
Classifier: Topic :: Security
Requires-Python: >=3.9
License-File: LICENSE
Dynamic: license-file
